promptfile/__init__.py
promptfile/prompt.py
promptfile/types.py
promptfile/utils.py
promptfile/clients/__init__.py
promptfile/clients/base_client.py
promptfile/clients/client.py
promptfile/clients/singleton_client.py
promptfile-0.8.0.dist-info/LICENSE
promptfile-0.8.0.dist-info/METADATA
promptfile-0.8.0.dist-info/WHEEL
promptfile-0.8.0.dist-info/top_level.txt
promptfile-0.8.0.dist-info/RECORD
