Metadata-Version: 2.1
Name: promptfile
Version: 0.8.0
Summary: promptfile: language support for .prompt files
Home-page: https://github.com/weavel-ai/promptfile
Author: weavel
Keywords: .prompt,prompt,prompt file,llm
Requires-Python: >=3.8.10
License-File: LICENSE
Requires-Dist: pydantic
Requires-Dist: pyyaml
